pmk_probes/__init__.py
pmk_probes/_data_structures.py
pmk_probes/_devices.py
pmk_probes/_errors.py
pmk_probes/_hardware_interfaces.py
pmk_probes/_version.py
pmk_probes/power_supplies.py
pmk_probes/probes.py
pmk_probes-1.0.16.dist-info/METADATA
pmk_probes-1.0.16.dist-info/WHEEL
pmk_probes-1.0.16.dist-info/licenses/LICENSE
pmk_probes-1.0.16.dist-info/RECORD
