Metadata-Version: 2.4
Name: pmk-probes
Version: 1.0.16
Summary: A Python package to control PMK's active oscilloscope probes.
Project-URL: Homepage, http://www.pmk.de/
Project-URL: Documentation, https://pmk-probes.readthedocs.io/en/latest/
Project-URL: Repository, https://github.com/PMK-Probing-Solutions/pmk-probes
Author-email: Felix Wenk <felix.wenk@pmk.de>
License-File: LICENSE
Classifier: Operating System :: OS Independent
Classifier: Programming Language :: Python :: 3
Requires-Python: >=3.10
Requires-Dist: pyserial>=3.5
